llmhub/__init__.py
llmhub/client.py
llmhub/main.py
llmhub-0.2.3.dist-info/METADATA
llmhub-0.2.3.dist-info/WHEEL
llmhub-0.2.3.dist-info/entry_points.txt
llmhub-0.2.3.dist-info/top_level.txt
llmhub-0.2.3.dist-info/RECORD
