Metadata-Version: 2.1
Name: llmhub
Version: 0.2.3
Author: LLMHub
Author-email: vatsal@llmhub.com
Requires-Python: >=3.9
Requires-Dist: requests (==2.28.1)
Requires-Dist: auth0-python (==3.24.0)
Requires-Dist: typer (==0.7.0)
Provides-Extra: dev
Requires-Dist: requests (==2.28.1) ; extra == 'dev'
Requires-Dist: auth0-python (==3.24.0) ; extra == 'dev'
Requires-Dist: typer (==0.7.0) ; extra == 'dev'
Requires-Dist: black ; extra == 'dev'
Requires-Dist: flake8 ; extra == 'dev'
Requires-Dist: isort ; extra == 'dev'
Requires-Dist: mypy ; extra == 'dev'
Requires-Dist: pytest ; extra == 'dev'
Requires-Dist: sphinx ; extra == 'dev'
Requires-Dist: twine ; extra == 'dev'
Provides-Extra: prod
Requires-Dist: requests (==2.28.1) ; extra == 'prod'
Requires-Dist: auth0-python (==3.24.0) ; extra == 'prod'
Requires-Dist: typer (==0.7.0) ; extra == 'prod'
